{
"type": "FeatureCollection",
"crs": { "type": "name", "properties": { "name": "urn:ogc:def:crs:OGC:1.3:CRS84" } },
"features": [
{ "type": "Feature", "properties": { "park": "ARRIGO (VICTOR)", "park_no": 215, "name": "Christopher Columbus and Fountain", "artist": "Moses Ezekiel", "owner": "CPD", "hash": "410a44369af7b95de7f68ec3e9e7893c" }, "geometry": { "type": "MultiPoint", "coordinates": [ [ -87.6613590206738, 41.871715571714965 ] ] } },
{ "type": "Feature", "properties": { "park": "BIXLER (RAY)", "park_no": 1083, "name": "Bixler Playlot Park Fountain", "artist": null, "owner": "CPD", "hash": "aa3e0e9040c797c369a4ae72b5107c01" }, "geometry": { "type": "MultiPoint", "coordinates": [ [ -87.592776015140757, 41.791679640917287 ] ] } },
{ "type": "Feature", "properties": { "park": "BURNHAM (DANIEL)", "park_no": 27, "name": "American Doughboy (Spirit of the American Doughboy)", "artist": "Ernest Moore Viquesney", "owner": "CPD", "hash": "4f9594596504e28f2b731f791720691e" }, "geometry": { "type": "MultiPoint", "coordinates": [ [ -87.616521315579703, 41.860805788922725 ] ] } },
{ "type": "Feature", "properties": { "park": "BURNHAM (DANIEL)", "park_no": 27, "name": "Mermaid (La Sirena)", "artist": "Jose Moreno", "owner": "CPD", "hash": "b4463a69c7ecfe0a1bc7b3d6ecf9b621" }, "geometry": { "type": "MultiPoint", "coordinates": [ [ -87.597196642101764, 41.820650951295391 ] ] } },
{ "type": "Feature", "properties": { "park": "BURNHAM (DANIEL)", "park_no": 27, "name": "Gold Star Families Memorial", "artist": "David Woodhouse & Assoc.", "owner": "CPD", "hash": "f4f4fcdf217a5c2f8aba2d04ab26480e" }, "geometry": { "type": "MultiPoint", "coordinates": [ [ -87.614228630581863, 41.862441377999268 ] ] } },
{ "type": "Feature", "properties": { "park": "BURNHAM (DANIEL)", "park_no": 27, "name": "Chicago Firefighter\/Paramedic Memorial", "artist": "John Alaniz", "owner": "CPD", "hash": "8c4908bd0d41bc35acb2fb91e83fa361" }, "geometry": { "type": "MultiPoint", "coordinates": [ [ -87.609772769100047, 41.850698585448995 ] ] } },
{ "type": "Feature", "properties": { "park": "BURNHAM (DANIEL)", "park_no": 27, "name": "Soldier Field Children's Garden", "artist": "Peter Lindsay Schaudt", "owner": null, "hash": "047966601fc01cb22925df241cd335fa" }, "geometry": { "type": "MultiPoint", "coordinates": [ [ -87.614842710973988, 41.864572810201437 ] ] } },
{ "type": "Feature", "properties": { "park": "BURNHAM (DANIEL)", "park_no": 27, "name": "Special Olympics Memorial", "artist": "Richard Hunt", "owner": "CPD", "hash": "ed09f2184228d85d76b5a5910a558062" }, "geometry": { "type": "MultiPoint", "coordinates": [ [ -87.615478525169976, 41.862175566927085 ] ] } },
{ "type": "Feature", "properties": { "park": "BURNHAM (DANIEL)", "park_no": 27, "name": "Tribute to Freedom", "artist": "Anna Koh Varilla", "owner": "CPD", "hash": "aa75fc663e6253cd7d69c53541dce6bc" }, "geometry": { "type": "MultiPoint", "coordinates": [ [ -87.617424010509396, 41.863459785266336 ] ] } },
{ "type": "Feature", "properties": { "park": "BURNHAM (DANIEL)", "park_no": 27, "name": "Tribute to George Halas", "artist": "Julie Rotblatt-Amrany", "owner": null, "hash": "2ddd567bf011eead5106740090a0a01e" }, "geometry": { "type": "MultiPoint", "coordinates": [ [ -87.615512766261062, 41.86253310539918 ] ] } },
{ "type": "Feature", "properties": { "park": "BURNHAM (DANIEL)", "park_no": 27, "name": "Wallach Fountain", "artist": "Frederick & Elisabeth Hibbard", "owner": "CPD", "hash": "bcfb8dac36a03c2b6f13004fa5712d94" }, "geometry": { "type": "MultiPoint", "coordinates": [ [ -87.575658403619414, 41.795573826291488 ] ] } },
{ "type": "Feature", "properties": { "park": "CANAL ORIGINS", "park_no": 502, "name": "Canal Cut Artwork", "artist": "Phil Schuster, CPAG", "owner": "CPD", "hash": "30931b3230e3bfa67f033ed3759a19a7" }, "geometry": { "type": "MultiPoint", "coordinates": [ [ -87.665508330062778, 41.842882618236182 ] ] } },
{ "type": "Feature", "properties": { "park": "CHICAGO WOMEN'S PARK AND GARDENS", "park_no": 550, "name": "Botanical Gardens Fountain", "artist": "Tannis Langdon", "owner": "CPD", "hash": "4f62e4cd427895bae2a3c834c8a30afe" }, "geometry": { "type": "MultiPoint", "coordinates": [ [ -87.621348432172653, 41.857077401972553 ] ] } },
{ "type": "Feature", "properties": { "park": "CHICAGO WOMEN'S PARK AND GARDENS", "park_no": 550, "name": "Jane Addams Memorial (Helping Hands)", "artist": "Louise Bourgeois", "owner": null, "hash": "25171e6ddd5c613ac37a4265d6ec654e" }, "geometry": { "type": "MultiPoint", "coordinates": [ [ -87.62123312437221, 41.856971589960395 ] ] } },
{ "type": "Feature", "properties": { "park": "COMMERCIAL CLUB PGD. OF CHICAGO", "park_no": 1006, "name": "Playground Art", "artist": "John Pittman Webber, CPAG", "owner": "CPD", "hash": "b3a00bdd9faff4bcd1f6d37df482e352" }, "geometry": { "type": "MultiPoint", "coordinates": [ [ -87.673769274822604, 41.896606957178292 ] ] } },
{ "type": "Feature", "properties": { "park": "CONNORS (WILLIAM)", "park_no": 1200, "name": "Connors Park Fountain", "artist": "Teng & Assoc.", "owner": "CPD", "hash": "338a98ae6a831d8ed8c37d4215773375" }, "geometry": { "type": "MultiPoint", "coordinates": [ [ -87.626692527651414, 41.898571441794104 ] ] } },
{ "type": "Feature", "properties": { "park": "DEARBORN (HENRY)", "park_no": 465, "name": "Alchemy -- Birds and Stone", "artist": "Dan Yarborough", "owner": "CPD", "hash": "122acc9ea816f961e59b3d7861afcd70" }, "geometry": { "type": "MultiPoint", "coordinates": [ [ -87.629133853196976, 41.87081540700251 ] ] } },
{ "type": "Feature", "properties": { "park": "CORNELL (PAUL) SQUARE", "park_no": 5, "name": "Paul Cornell Bust", "artist": "Sigvald Asbjørnsen", "owner": "CPD", "hash": "3a8de666c6eda09a9d47302e6bd56d33" }, "geometry": { "type": "MultiPoint", "coordinates": [ [ -87.670123338422655, 41.802959038228174 ] ] } },
{ "type": "Feature", "properties": { "park": "FULLER (MELVILLE)", "park_no": 4, "name": "Melville W. Fuller Bust", "artist": "William Ordway Partridge", "owner": "CPD", "hash": "1ca136cb296aec4b0fae6bcc24b381a9" }, "geometry": { "type": "MultiPoint", "coordinates": [ [ -87.634598348959983, 41.812175287689257 ] ] } },
{ "type": "Feature", "properties": { "park": "FULLER (MELVILLE)", "park_no": 4, "name": "Fountain", "artist": null, "owner": "CPD", "hash": "1fc49a349ead578e6693a1faf596c535" }, "geometry": { "type": "MultiPoint", "coordinates": [ [ -87.634592308521448, 41.812060808229823 ] ] } },
{ "type": "Feature", "properties": { "park": "GARFIELD (JAMES)", "park_no": 204, "name": "Administration Bldg Interior Panels (Gold Dome Rotunda Panels)", "artist": "Richard W. Bock", "owner": "CPD", "hash": "ec3bc9620f229e39167a63482573e4f0" }, "geometry": { "type": "MultiPoint", "coordinates": [ [ -87.716013422852086, 41.88267268817728 ] ] } },
{ "type": "Feature", "properties": { "park": "GARFIELD (JAMES)", "park_no": 204, "name": "Bulls with Maidens (World Fair Bulls\/Statues of Plenty)", "artist": "Daniel Chester French, Edward C. Potter", "owner": "CPD", "hash": "971d3d5906085acc4178258715232f5f" }, "geometry": { "type": "MultiPoint", "coordinates": [ [ -87.71865303467797, 41.886595393985601 ] ] } },
{ "type": "Feature", "properties": { "park": "GARFIELD (JAMES)", "park_no": 204, "name": "Norman Cornwall Memorial (WWI Obelisk)", "artist": "Carl J. Epiing", "owner": "CPD", "hash": "c8ae6d5e3ad021314c7efb8d41f709fa" }, "geometry": { "type": "MultiPoint", "coordinates": [ [ -87.716005633825375, 41.877058313542676 ] ] } },
{ "type": "Feature", "properties": { "park": "GARFIELD (JAMES)", "park_no": 204, "name": "Robert Burns Memorial", "artist": "William Grant Stevenson", "owner": "CPD", "hash": "8994af0a203c9017c52fa418c2d68c74" }, "geometry": { "type": "MultiPoint", "coordinates": [ [ -87.717360736203162, 41.881990705705995 ] ] } },
{ "type": "Feature", "properties": { "park": "GARFIELD (JAMES)", "park_no": 204, "name": "Conservatory Entrance Fountain", "artist": "Wolff, Clements & Assoc", "owner": "CPD", "hash": "6e17acd0543cc4a58b3220154226e6ab" }, "geometry": { "type": "MultiPoint", "coordinates": [ [ -87.716825453538902, 41.88627571866693 ] ] } },
{ "type": "Feature", "properties": { "park": "GARFIELD (JAMES)", "park_no": 204, "name": "Lincoln the Rail-Splitter", "artist": "Charles J. Mulligan", "owner": "CPD", "hash": "868e2ea7ddf1395ffa8506dd56c4a7f5" }, "geometry": { "type": "MultiPoint", "coordinates": [ [ -87.716068759847545, 41.881787638152574 ] ] } },
{ "type": "Feature", "properties": { "park": "GARFIELD (JAMES)", "park_no": 204, "name": "Pastoral & Idyl", "artist": "Lorado Taft", "owner": "CPD", "hash": "7d83b9fcd8c80a6d9968aa59746a902e" }, "geometry": { "type": "MultiPoint", "coordinates": [ [ -87.717300149244082, 41.886334643645029 ] ] } },
{ "type": "Feature", "properties": { "park": "GARFIELD (JAMES)", "park_no": 204, "name": "Persian Pool (Yellow Lilies)", "artist": "Dale Chihuly", "owner": "CPD", "hash": "8423261aec1e5c2f88319818621e198d" }, "geometry": { "type": "MultiPoint", "coordinates": [ [ -87.717456759597468, 41.88629260490373 ] ] } },
{ "type": "Feature", "properties": { "park": "GARFIELD (JAMES)", "park_no": 204, "name": "Zellij Fountain", "artist": "Said Ben Adiba", "owner": "CPD", "hash": "6c48cc1fdc325d0aa65d4630fc2a08ae" }, "geometry": { "type": "MultiPoint", "coordinates": [ [ -87.717677224968327, 41.886572499350308 ] ] } },
{ "type": "Feature", "properties": { "park": "GARIBALDI (GIUSEPPE)", "park_no": 1047, "name": "Giuseppe Garibaldi Monument", "artist": "Victor Gheradi", "owner": "CPD", "hash": "20e3bce420918be7b1113ac8173b9e75" }, "geometry": { "type": "MultiPoint", "coordinates": [ [ -87.665310802824095, 41.872591757506704 ] ] } },
{ "type": "Feature", "properties": { "park": "GOMPERS (SAMUEL)", "park_no": 40, "name": "Samuel Gompers Monument", "artist": "Susan Clinard", "owner": "CPD", "hash": "56a25baf4037e2f05352a11368f44725" }, "geometry": { "type": "MultiPoint", "coordinates": [ [ -87.728550984391831, 41.975287947979105 ] ] } },
{ "type": "Feature", "properties": { "park": "GOUDY (WILLIAM) SQUARE", "park_no": 105, "name": "Goudy Square Playground Art", "artist": "Walter Arnold", "owner": "CPD", "hash": "c07b3be807f46e9db26ab6d4e8b26c75" }, "geometry": { "type": "MultiPoint", "coordinates": [ [ -87.626875126422703, 41.905506494682697 ] ] } },
{ "type": "Feature", "properties": { "park": "GRANT (ULYSSES)", "park_no": 24, "name": "Agora", "artist": "Magdalena Abakanowicz", "owner": "CPD", "hash": "de21a5486d7907840cbe9c1f392dcb4a" }, "geometry": { "type": "MultiPoint", "coordinates": [ [ -87.623367141160742, 41.868090468946384 ] ] } },
{ "type": "Feature", "properties": { "park": "GRANT (ULYSSES)", "park_no": 24, "name": "Big Beaver Totem Pole", "artist": "Norman Tait Nishga", "owner": "Field Museum", "hash": "5421cbc8c04530e73e8d36f9794367d7" }, "geometry": { "type": "MultiPoint", "coordinates": [ [ -87.617029065454162, 41.86720060683836 ] ] } },
{ "type": "Feature", "properties": { "park": "GRANT (ULYSSES)", "park_no": 24, "name": "Central Station Fragments", "artist": "Bradford L. Gilbert", "owner": "Metra", "hash": "9ae8fb958da90fec142e47b4df445f56" }, "geometry": { "type": "MultiPoint", "coordinates": [ [ -87.622023251957401, 41.867768808941541 ] ] } },
{ "type": "Feature", "properties": { "park": "GRANT (ULYSSES)", "park_no": 24, "name": "Clarence Buckingham Memorial Fountain", "artist": "Marcel Francois Loyau", "owner": "CPD", "hash": "7e204d80b41ceed24390b433799c4027" }, "geometry": { "type": "MultiPoint", "coordinates": [ [ -87.61893954497765, 41.875795890638685 ] ] } },
{ "type": "Feature", "properties": { "park": "GRANT (ULYSSES)", "park_no": 24, "name": "Chicago Stock Exchange Arch", "artist": "Adler & Sullivan", "owner": "Art Institute of Chicago", "hash": "60cbde5f7628961db78f8d8cf3257960" }, "geometry": { "type": "MultiPoint", "coordinates": [ [ -87.621063212826826, 41.880647392557826 ] ] } },
{ "type": "Feature", "properties": { "park": "GRANT (ULYSSES)", "park_no": 24, "name": "Christopher Columbus Monument", "artist": "Carl Brioschi", "owner": "CPD", "hash": "94feea4bed1f15b9755727d6a94e9bd2" }, "geometry": { "type": "MultiPoint", "coordinates": [ [ -87.619617307669927, 41.867928416125402 ] ] } },
{ "type": "Feature", "properties": { "park": "GRANT (ULYSSES)", "park_no": 24, "name": "Core-Loc Armoring Devices", "artist": "US Army Corps of Engineers", "owner": "CPD", "hash": "a4a918d7aae3f477701bd4a806739278" }, "geometry": { "type": "MultiPoint", "coordinates": [ [ -87.613163248453532, 41.886421296045143 ] ] } },
{ "type": "Feature", "properties": { "park": "GRANT (ULYSSES)", "park_no": 24, "name": "Cubi VII", "artist": "David Smith", "owner": "Art Institute of Chicago", "hash": "7eb9a01f72da512a7a012574e5b82b8b" }, "geometry": { "type": "MultiPoint", "coordinates": [ [ -87.623801769266379, 41.880322505958198 ] ] } },
{ "type": "Feature", "properties": { "park": "GRANT (ULYSSES)", "park_no": 24, "name": "Eagle Fountains", "artist": "Frederick Cleveland Hibbard", "owner": "CPD", "hash": "d45e7587d5e27f49b7fd0c6595720198" }, "geometry": { "type": "MultiPoint", "coordinates": [ [ -87.623704032724035, 41.875471237057383 ] ] } },
{ "type": "Feature", "properties": { "park": "GRANT (ULYSSES)", "park_no": 24, "name": "Equestrian Indians", "artist": "Ivan Mestrovic", "owner": "COD", "hash": "9c392ff06169958b6455c664a17930a7" }, "geometry": { "type": "MultiPoint", "coordinates": [ [ -87.623558369627204, 41.875961061394868 ] ] } },
{ "type": "Feature", "properties": { "park": "GRANT (ULYSSES)", "park_no": 24, "name": "8th Street Fountain", "artist": "Bennett, Frost & Thomas", "owner": "CPD", "hash": "8e51885b0b620241f2fd21ecedcbedd5" }, "geometry": { "type": "MultiPoint", "coordinates": [ [ -87.623335362318173, 41.871919544077059 ] ] } },
{ "type": "Feature", "properties": { "park": "GRANT (ULYSSES)", "park_no": 24, "name": "Federal Building Columns", "artist": "Henry Ives Cobb", "owner": "CPD", "hash": "a6dffeb101cfd59412513c8ff1995236" }, "geometry": { "type": "MultiPoint", "coordinates": [ [ -87.617449622096032, 41.884113944848728 ] ] } },
{ "type": "Feature", "properties": { "park": "GRANT (ULYSSES)", "park_no": 24, "name": "Flying Dragon", "artist": "Alexander Calder", "owner": "Art Institute of Chicago", "hash": "fe7233041ba12857ff016581d602936a" }, "geometry": { "type": "MultiPoint", "coordinates": [ [ -87.623757788115611, 41.88040834905253 ] ] } },
{ "type": "Feature", "properties": { "park": "GRANT (ULYSSES)", "park_no": 24, "name": "Fountain Figures", "artist": "Leonard Crunelle", "owner": "CPD", "hash": "0daa75d542d5c60d676c89d7cfeec353" }, "geometry": { "type": "MultiPoint", "coordinates": [ [ -87.618085741978049, 41.877725635113201 ] ] } },
{ "type": "Feature", "properties": { "park": "GRANT (ULYSSES)", "park_no": 24, "name": "Fountain Figures", "artist": "Leonard Crunelle", "owner": "CPD", "hash": "cbbbabeaab3f3492580dc1b4e87c06a9" }, "geometry": { "type": "MultiPoint", "coordinates": [ [ -87.619902864144734, 41.877701206297495 ] ] } },
{ "type": "Feature", "properties": { "park": "GRANT (ULYSSES)", "park_no": 24, "name": "Fountain Figures", "artist": "Leonard Crunelle", "owner": "CPD", "hash": "265d0eae3277bb794aa4691006f305aa" }, "geometry": { "type": "MultiPoint", "coordinates": [ [ -87.619802098946082, 41.873865308431682 ] ] } },
{ "type": "Feature", "properties": { "park": "GRANT (ULYSSES)", "park_no": 24, "name": "Fountain Figures", "artist": "Leonard Crunelle", "owner": "CPD", "hash": "9117bf5a0b25449f8a80bbba5e390c95" }, "geometry": { "type": "MultiPoint", "coordinates": [ [ -87.618001153239973, 41.873877925986527 ] ] } },
{ "type": "Feature", "properties": { "park": "GRANT (ULYSSES)", "park_no": 24, "name": "Fountain of the Great Lakes (Spirit of the Great Lakes)", "artist": "Lorado Taft", "owner": "Art Institute of Chicago", "hash": "bb431bdd97a2ea6410dc49ac31d47170" }, "geometry": { "type": "MultiPoint", "coordinates": [ [ -87.623652340501934, 41.878760676107959 ] ] } },
{ "type": "Feature", "properties": { "park": "GRANT (ULYSSES)", "park_no": 24, "name": "In Celebration of the 200th Anniversary of the Founding of the Republic", "artist": "Isamu Noguchi", "owner": "Art Institute of Chicago", "hash": "7376ec0a9ae41a3b11620de9cd50df84" }, "geometry": { "type": "MultiPoint", "coordinates": [ [ -87.621100193913108, 41.880388562557215 ] ] } },
{ "type": "Feature", "properties": { "park": "GRANT (ULYSSES)", "park_no": 24, "name": "Abraham Lincoln (Seated Lincoln)", "artist": "Augustus Saint-Gaudens", "owner": "CPD", "hash": "6e42734dcdce831d2b444c3c1e7c7fde" }, "geometry": { "type": "MultiPoint", "coordinates": [ [ -87.621516780711616, 41.877318164899435 ] ] } },
{ "type": "Feature", "properties": { "park": "GRANT (ULYSSES)", "park_no": 24, "name": "Lions", "artist": "Edward Kemeys", "owner": "Art Institute of Chicago", "hash": "950b01bf8449d33597199319e147b58f" }, "geometry": { "type": "MultiPoint", "coordinates": [ [ -87.624043430957528, 41.879569302978325 ] ] } },
{ "type": "Feature", "properties": { "park": "GRANT (ULYSSES)", "park_no": 24, "name": "John Alexander Logan Monument", "artist": "Augustus Saint-Gaudens, Alexander Proctor", "owner": "CPD", "hash": "797527f7ffda46e02278a67c31aa184b" }, "geometry": { "type": "MultiPoint", "coordinates": [ [ -87.623444538430178, 41.870607500227287 ] ] } },
{ "type": "Feature", "properties": { "park": "GRANT (ULYSSES)", "park_no": 24, "name": "Man With Fish", "artist": "Stephan Balkenhol", "owner": "Shedd Aquarium", "hash": "a9f2da5028a58628bc2ae78a440e8578" }, "geometry": { "type": "MultiPoint", "coordinates": [ [ -87.614650031718554, 41.867130413295421 ] ] } },
{ "type": "Feature", "properties": { "park": "GRANT (ULYSSES)", "park_no": 24, "name": "Olmec Head", "artist": "Ignacio Perez Salono", "owner": "Field Museum", "hash": "768ab4603e196d7dcb4ff5524c6fee6c" }, "geometry": { "type": "MultiPoint", "coordinates": [ [ -87.615822184642525, 41.867044838885086 ] ] } },
{ "type": "Feature", "properties": { "park": "GRANT (ULYSSES)", "park_no": 24, "name": "Paris Metro Entryway (Guimard)", "artist": "Hector Guimard", "owner": "COC", "hash": "0e00111d3992563d8d2f7a949e6ebc7c" }, "geometry": { "type": "MultiPoint", "coordinates": [ [ -87.623906476184871, 41.876976730480024 ] ] } },
{ "type": "Feature", "properties": { "park": "GRANT (ULYSSES)", "park_no": 24, "name": "Reading Cones", "artist": "Richard Serra", "owner": "COC", "hash": "05157a156b3f9cdb6f0401cb298b5197" }, "geometry": { "type": "MultiPoint", "coordinates": [ [ -87.619051500728403, 41.880602530420717 ] ] } },
{ "type": "Feature", "properties": { "park": "GRANT (ULYSSES)", "park_no": 24, "name": "Rosenberg Fountain (Hebe)", "artist": "Franz Machtl", "owner": "CPD", "hash": "12daf7630704027c58ffdc2db137027d" }, "geometry": { "type": "MultiPoint", "coordinates": [ [ -87.62377340866135, 41.868691239949399 ] ] } },
{ "type": "Feature", "properties": { "park": "GRANT (ULYSSES)", "park_no": 24, "name": "Sir Georg Solti Bust", "artist": "Dame Elisabeth Frink", "owner": "CPD", "hash": "8572a18f35f4cd68125851bde0c5c36f" }, "geometry": { "type": "MultiPoint", "coordinates": [ [ -87.623956252319232, 41.878095937190672 ] ] } },
{ "type": "Feature", "properties": { "park": "GRANT (ULYSSES)", "park_no": 24, "name": "Spirit of Music (Theodore Thomas Memorial)", "artist": "Albin Polasek", "owner": "CPD", "hash": "ab7ba539bf157bb1b7d548dde1358b44" }, "geometry": { "type": "MultiPoint", "coordinates": [ [ -87.623498548938656, 41.873370483314154 ] ] } },
{ "type": "Feature", "properties": { "park": "GRANT (ULYSSES)", "park_no": 24, "name": "Aaron Montgomery Ward Bust", "artist": "Milton Horn", "owner": "CPD", "hash": "4053112270deaaa02f9602b99c6a8917" }, "geometry": { "type": "MultiPoint", "coordinates": [ [ -87.623591152919943, 41.869321385806813 ] ] } },
{ "type": "Feature", "properties": { "park": "HARRISON (CARTER)", "park_no": 213, "name": "Zapata Bust", "artist": "Gabriel Ponzanelli", "owner": "CPD", "hash": "44bd4997249d4a159923915cac8df892" }, "geometry": { "type": "MultiPoint", "coordinates": [ [ -87.671710495960497, 41.85680241801537 ] ] } },
{ "type": "Feature", "properties": { "park": "HERITAGE GREEN", "park_no": 537, "name": "Grainne", "artist": "Maurice Harron", "owner": "CPD", "hash": "c0deb40acd5f5f658116af1cfce775dc" }, "geometry": { "type": "MultiPoint", "coordinates": [ [ -87.643786424369551, 41.879450970306529 ] ] } },
{ "type": "Feature", "properties": { "park": "HORNER (HENRY)", "park_no": 228, "name": "Henry Horner Monument", "artist": "John David Brcin", "owner": "CPD", "hash": "15b11556af03710b6da00088f22d06ee" }, "geometry": { "type": "MultiPoint", "coordinates": [ [ -87.698229808383601, 41.961088722856431 ] ] } },
{ "type": "Feature", "properties": { "park": "HUMBOLDT (BARON VON)", "park_no": 219, "name": "World's Fair Bison", "artist": "Edward Kemeys", "owner": "CPD", "hash": "61fd702b6125c2372cf067bf7bbbca2d" }, "geometry": { "type": "MultiPoint", "coordinates": [ [ -87.702406147490422, 41.903801066057817 ] ] } },
{ "type": "Feature", "properties": { "park": "HUMBOLDT (BARON VON)", "park_no": 219, "name": "Leif Ericsson Monument", "artist": "Sigvald Asbjørnsen", "owner": "CPD", "hash": "717c5becbedaf810b8b040e897791522" }, "geometry": { "type": "MultiPoint", "coordinates": [ [ -87.701559496383098, 41.90671573425989 ] ] } },
{ "type": "Feature", "properties": { "park": "HUMBOLDT (BARON VON)", "park_no": 219, "name": "Alexander von Humboldt Monument", "artist": "Felix Gorling", "owner": "CPD", "hash": "aa9969f4c297c33713251d0dc18878ad" }, "geometry": { "type": "MultiPoint", "coordinates": [ [ -87.701456962308313, 41.905471689269966 ] ] } },
{ "type": "Feature", "properties": { "park": "HUMBOLDT (BARON VON)", "park_no": 219, "name": "Home (Miner and Child)", "artist": "Charles Mulligan", "owner": "CPD", "hash": "a2a1847bbedb30c6242227c3ab578101" }, "geometry": { "type": "MultiPoint", "coordinates": [ [ -87.697559535914507, 41.903449171089214 ] ] } },
{ "type": "Feature", "properties": { "park": "HUMBOLDT (BARON VON)", "park_no": 219, "name": "Interpreting Nature", "artist": "Roman Villareal", "owner": "CPD", "hash": "c2cef35bb3e362bab50dbc11856b4f26" }, "geometry": { "type": "MultiPoint", "coordinates": [ [ -87.699420470810068, 41.906255149024879 ] ] } },
{ "type": "Feature", "properties": { "park": "HUMBOLDT (BARON VON)", "park_no": 219, "name": "Fritz Reuter", "artist": "Franz Engelsman", "owner": "CPD", "hash": "a9de1dcc66576d8011f1ef473ca9214a" }, "geometry": { "type": "MultiPoint", "coordinates": [ [ -87.701919225098095, 41.903801010557792 ] ] } },
{ "type": "Feature", "properties": { "park": "INDIAN BOUNDARY", "park_no": 165, "name": "City Hall Keystone", "artist": "A.C. Goddard", "owner": "CPD", "hash": "8247489e61fcd7e4d90f67460da9d5fc" }, "geometry": { "type": "MultiPoint", "coordinates": [ [ -87.692188534872813, 42.009120008195204 ] ] } },
{ "type": "Feature", "properties": { "park": "INDIAN BOUNDARY", "park_no": 165, "name": "Wind Harp", "artist": "Craig Brant", "owner": "Craig Brant", "hash": "eef3aa13fbe8264748a10939245737f1" }, "geometry": { "type": "MultiPoint", "coordinates": [ [ -87.692150503833957, 42.009599265610468 ] ] } },
{ "type": "Feature", "properties": { "park": "JACKSON (ANDREW)", "park_no": 19, "name": "The Republic (Golden Lady)", "artist": "Daniel Chester French", "owner": "CPD", "hash": "f7a0ccf5c3219afaf0f41d5309b90bdd" }, "geometry": { "type": "MultiPoint", "coordinates": [ [ -87.579896078796338, 41.779598010045582 ] ] } },
{ "type": "Feature", "properties": { "park": "JONQUIL", "park_no": 1270, "name": "Eagle Columns", "artist": "Richard Hunt", "owner": "CPD", "hash": "fd4caf662467a57197affbb54fe95406" }, "geometry": { "type": "MultiPoint", "coordinates": [ [ -87.653940272040444, 41.928852585316228 ] ] } },
{ "type": "Feature", "properties": { "park": "KENNEDY (DENNIS)", "park_no": 48, "name": "Playground Art", "artist": "Roman Villareal", "owner": "CPD", "hash": "b8b8c16d18e1f82961dd5b4681cf9f7c" }, "geometry": { "type": "MultiPoint", "coordinates": [ [ -87.681958729317302, 41.687674658755057 ] ] } },
{ "type": "Feature", "properties": { "park": "KING (MARTIN LUTHER, JR.)", "park_no": 265, "name": "Dr. Martin Luther King Bust", "artist": "Tina Allen", "owner": "CPD", "hash": "b97392b1de59923e7a2517429ae2400b" }, "geometry": { "type": "MultiPoint", "coordinates": [ [ -87.654667706378746, 41.755820708281654 ] ] } },
{ "type": "Feature", "properties": { "park": "LEGION", "park_no": 274, "name": "Legion Park Gateway Plaza Fountain", "artist": "DeStefano & Partners", "owner": "CPD", "hash": "bb9fdab00533486809446bcf2669bedd" }, "geometry": { "type": "MultiPoint", "coordinates": [ [ -87.707955753275655, 41.98995161543332 ] ] } },
{ "type": "Feature", "properties": { "park": "LINCOLN (ABRAHAM)", "park_no": 100, "name": "The Alarm", "artist": "John J. Boyle", "owner": "CPD", "hash": "c4e127009fa6b3360f2797c5496cba03" }, "geometry": { "type": "MultiPoint", "coordinates": [ [ -87.635883517145771, 41.93663304267114 ] ] } },
{ "type": "Feature", "properties": { "park": "LINCOLN (ABRAHAM)", "park_no": 100, "name": "John Peter Altgeld Monument", "artist": "Gutzon Borglum", "owner": "CPD", "hash": "309f8176c42c8e406e9ecc4d595cf94c" }, "geometry": { "type": "MultiPoint", "coordinates": [ [ -87.637530334359283, 41.932186833469359 ] ] } },
{ "type": "Feature", "properties": { "park": "LINCOLN (ABRAHAM)", "park_no": 100, "name": "Hans Christian Andersen", "artist": "Johannes Gelert", "owner": "CPD", "hash": "1eb8dd4e94e2c6ba11be83fa2b1c9427" }, "geometry": { "type": "MultiPoint", "coordinates": [ [ -87.634661877357885, 41.919602570373641 ] ] } },
{ "type": "Feature", "properties": { "park": "LINCOLN (ABRAHAM)", "park_no": 100, "name": "Eli Bates Fountain (Storks at Play)", "artist": "Augustus Saint-Gaudens, Frederick MacMonnies", "owner": "CPD", "hash": "35941b24c6a12b368746749fa40d712c" }, "geometry": { "type": "MultiPoint", "coordinates": [ [ -87.635213806517811, 41.922735462688209 ] ] } },
{ "type": "Feature", "properties": { "park": "LINCOLN (ABRAHAM)", "park_no": 100, "name": "Greene Vardiman Black", "artist": "Frederick Cleveland Hibbard", "owner": "CPD", "hash": "8465f0a6801bc12133946a31f8856e4b" }, "geometry": { "type": "MultiPoint", "coordinates": [ [ -87.627593388359827, 41.91134021289696 ] ] } },
{ "type": "Feature", "properties": { "park": "LINCOLN (ABRAHAM)", "park_no": 100, "name": "Chess Pavillion", "artist": "Boris Gilbertson", "owner": "CPD", "hash": "6a80543ab84b960cd6e9797d656ccb79" }, "geometry": { "type": "MultiPoint", "coordinates": [ [ -87.624986781703385, 41.911294385922695 ] ] } },
{ "type": "Feature", "properties": { "park": "LINCOLN (ABRAHAM)", "park_no": 100, "name": "Chicago Fire Relic", "artist": null, "owner": "Chicago History Museum", "hash": "1eaa12bdd7a862da2c3adf18a2c899b5" }, "geometry": { "type": "MultiPoint", "coordinates": [ [ -87.630737823300109, 41.911947915671099 ] ] } },
{ "type": "Feature", "properties": { "park": "LINCOLN (ABRAHAM)", "park_no": 100, "name": "City Hall Relic (Finial)", "artist": "Jenney & Loring", "owner": "CPD", "hash": "3757d6c4d26277fd2e78dcd2dded8497" }, "geometry": { "type": "MultiPoint", "coordinates": [ [ -87.636106997781667, 41.918856304333367 ] ] } },
{ "type": "Feature", "properties": { "park": "LINCOLN (ABRAHAM)", "park_no": 100, "name": "Couch Tomb", "artist": "Van Osdel & Baumann", "owner": "CPD", "hash": "7ae231801cb1455c5efe85352a8b72d9" }, "geometry": { "type": "MultiPoint", "coordinates": [ [ -87.631691006419842, 41.913014916231468 ] ] } },
{ "type": "Feature", "properties": { "park": "LINCOLN (ABRAHAM)", "park_no": 100, "name": "Cummings Playground Art", "artist": "Tom Tischler", "owner": "CPD", "hash": "04c7264b9286f88e2aec493b673ed2ef" }, "geometry": { "type": "MultiPoint", "coordinates": [ [ -87.635971463380329, 41.92074401088405 ] ] } },
{ "type": "Feature", "properties": { "park": "LINCOLN (ABRAHAM)", "park_no": 100, "name": "Curve XXII (I Will)", "artist": "Ellsworth Kelly", "owner": "CPD", "hash": "fad25de70436cabbc05f54bea0e05354" }, "geometry": { "type": "MultiPoint", "coordinates": [ [ -87.633380790125628, 41.926135700480671 ] ] } },
{ "type": "Feature", "properties": { "park": "LINCOLN (ABRAHAM)", "park_no": 100, "name": "Robert Cavalier de LaSalle", "artist": "Count Jacque de la Laing", "owner": "CPD", "hash": "fa384b3dd36d1140f560a799765487ad" }, "geometry": { "type": "MultiPoint", "coordinates": [ [ -87.632742964076868, 41.913365280987072 ] ] } },
{ "type": "Feature", "properties": { "park": "LINCOLN (ABRAHAM)", "park_no": 100, "name": "Children's Fountain", "artist": "Robinson Iron Works", "owner": "CPD", "hash": "0e69b9898bcdd3e24b77bee83f944709" }, "geometry": { "type": "MultiPoint", "coordinates": [ [ -87.631425695108788, 41.911338371026716 ] ] } },
{ "type": "Feature", "properties": { "park": "LINCOLN (ABRAHAM)", "park_no": 100, "name": "Benjamin Franklin", "artist": "Richard Henry Park", "owner": "CPD", "hash": "999939f669515600192948137cf8671e" }, "geometry": { "type": "MultiPoint", "coordinates": [ [ -87.631087830694739, 41.913794676355074 ] ] } },
{ "type": "Feature", "properties": { "park": "LINCOLN (ABRAHAM)", "park_no": 100, "name": "Garden Figure", "artist": "Frederick C. Hibbard", "owner": "CPD", "hash": "bd47a72df8904d701b719a7b4b00e679" }, "geometry": { "type": "MultiPoint", "coordinates": [ [ -87.635217168682445, 41.924177994283006 ] ] } },
{ "type": "Feature", "properties": { "park": "LINCOLN (ABRAHAM)", "park_no": 100, "name": "Goddess of Youth (Hebe)", "artist": null, "owner": "CPD", "hash": "7a106f70edf0194b8654fa04ddbb670e" }, "geometry": { "type": "MultiPoint", "coordinates": [ [ -87.63538229805566, 41.92424569847438 ] ] } },
{ "type": "Feature", "properties": { "park": "LINCOLN (ABRAHAM)", "park_no": 100, "name": "Monument to Johann Wolfgang von Goethe", "artist": "Herman Hahn", "owner": "CPD", "hash": "f1d9a45b3234287176851109ce608254" }, "geometry": { "type": "MultiPoint", "coordinates": [ [ -87.638608991593074, 41.932602742694442 ] ] } },
{ "type": "Feature", "properties": { "park": "LINCOLN (ABRAHAM)", "park_no": 100, "name": "Ulysses S. Grant Memorial", "artist": "Louis T. Rebisso", "owner": "CPD", "hash": "01023220643f77a2a3ab02d5fa41b965" }, "geometry": { "type": "MultiPoint", "coordinates": [ [ -87.630862699963131, 41.917529091213879 ] ] } },
{ "type": "Feature", "properties": { "park": "LINCOLN (ABRAHAM)", "park_no": 100, "name": "Alexander Hamilton", "artist": "John Angel", "owner": "CPD", "hash": "0e1179c08d9c0a073fb23a2689a6fe53" }, "geometry": { "type": "MultiPoint", "coordinates": [ [ -87.63842731481428, 41.931705961019738 ] ] } },
{ "type": "Feature", "properties": { "park": "LINCOLN (ABRAHAM)", "park_no": 100, "name": "Abraham Lincoln Monument  (Standing Lincoln)", "artist": "Augustus Saint-Gaudens", "owner": "CPD", "hash": "5b30269ca2c4aeb741cd80bcbf086ddd" }, "geometry": { "type": "MultiPoint", "coordinates": [ [ -87.630266269245837, 41.912589644301214 ] ] } },
{ "type": "Feature", "properties": { "park": "LINCOLN (ABRAHAM)", "park_no": 100, "name": "Margate Park Playground Art", "artist": "CPAG", "owner": "CPD", "hash": "eab6633c4bfb98f907072d2e0be12ab7" }, "geometry": { "type": "MultiPoint", "coordinates": [ [ -87.649437994992525, 41.97246356294491 ] ] } },
{ "type": "Feature", "properties": { "park": "LINCOLN (ABRAHAM)", "park_no": 100, "name": "Richard Oglesby Monument", "artist": "Leonard Crunelle", "owner": "CPD", "hash": "f62d42782d7f3dd2a64b2811e349ee2e" }, "geometry": { "type": "MultiPoint", "coordinates": [ [ -87.637065641210512, 41.930147655876056 ] ] } },
{ "type": "Feature", "properties": { "park": "LINCOLN (ABRAHAM)", "park_no": 100, "name": "Putnam Chain", "artist": null, "owner": "Chicago History Museum", "hash": "f1b8626a4b34c73cbe030cfd6caf83c0" }, "geometry": { "type": "MultiPoint", "coordinates": [ [ -87.631101729694166, 41.912410378819239 ] ] } },
{ "type": "Feature", "properties": { "park": "LINCOLN (ABRAHAM)", "park_no": 100, "name": "Kwa-Ma-Rolas (Totem Pole)", "artist": "Haida Indians", "owner": "CPD", "hash": "013361f9d312c305e6686770c142d09b" }, "geometry": { "type": "MultiPoint", "coordinates": [ [ -87.64242274936619, 41.948972176948644 ] ] } },
{ "type": "Feature", "properties": { "park": "LINCOLN (ABRAHAM)", "park_no": 100, "name": "Dr. Jose Rizal", "artist": "Antonio T. Mondejar", "owner": "CPD", "hash": "5b579f87db64913d47f42b8bbc21c61b" }, "geometry": { "type": "MultiPoint", "coordinates": [ [ -87.648173718648096, 41.967148066500222 ] ] } },
{ "type": "Feature", "properties": { "park": "LINCOLN (ABRAHAM)", "park_no": 100, "name": "Roscoe Playground Art", "artist": "CPAG", "owner": "CPD", "hash": "ae7e489b28c750de22178efe32a07b2a" }, "geometry": { "type": "MultiPoint", "coordinates": [ [ -87.638995296123383, 41.943016783448847 ] ] } },
{ "type": "Feature", "properties": { "park": "LINCOLN (ABRAHAM)", "park_no": 100, "name": "Johann Christoph Friedrich von Schiller", "artist": "Ernst Bilhauer Rau", "owner": "CPD", "hash": "52b48984a7f75a6a2667e2cbbc45ec40" }, "geometry": { "type": "MultiPoint", "coordinates": [ [ -87.635194686623507, 41.921997606511717 ] ] } },
{ "type": "Feature", "properties": { "park": "LINCOLN (ABRAHAM)", "park_no": 100, "name": "William Shakespeare", "artist": "William Ordway Partridge", "owner": "CPD", "hash": "028752d0748c407c52a71a77e1627fc8" }, "geometry": { "type": "MultiPoint", "coordinates": [ [ -87.636194034842148, 41.923811720750933 ] ] } },
{ "type": "Feature", "properties": { "park": "LINCOLN (ABRAHAM)", "park_no": 100, "name": "Gen. Philip Henry Sheridan Monument", "artist": "Gutzon Borglum", "owner": "CPD", "hash": "d899d6c41b8245f6849bed449bf7db8c" }, "geometry": { "type": "MultiPoint", "coordinates": [ [ -87.639238516970039, 41.940449126223164 ] ] } },
{ "type": "Feature", "properties": { "park": "LINCOLN (ABRAHAM)", "park_no": 100, "name": "Signal of Peace", "artist": "Cyrus Edwin Dallin", "owner": "CPD", "hash": "c32625c4dd4e758468cb41d033e4d5f5" }, "geometry": { "type": "MultiPoint", "coordinates": [ [ -87.631377394534937, 41.933206104058748 ] ] } },
{ "type": "Feature", "properties": { "park": "LINCOLN (ABRAHAM)", "park_no": 100, "name": "Emanuel Swedenborg Memorial", "artist": "Adolff Johnson", "owner": "CPD", "hash": "c6509f325128eeb7ae595b288f91028b" }, "geometry": { "type": "MultiPoint", "coordinates": [ [ -87.631686173944487, 41.931448189277432 ] ] } },
{ "type": "Feature", "properties": { "park": "LOGAN SQUARE SKATE PARK", "park_no": 549, "name": "Silversurf Gate", "artist": "Lucy Slivinski", "owner": null, "hash": "568f1e5e9edab904d66597a311f0ab03" }, "geometry": { "type": "MultiPoint", "coordinates": [ [ -87.689569407779018, 41.928492869182364 ] ] } },
{ "type": "Feature", "properties": { "park": "LOYOLA", "park_no": 115, "name": "Windform", "artist": "Lynn Takata", "owner": "CPD", "hash": "a749cfe840823b7584807a3be358b6e1" }, "geometry": { "type": "MultiPoint", "coordinates": [ [ -87.658182461153217, 42.005942277480649 ] ] } },
{ "type": "Feature", "properties": { "park": "MARIANO (LOUIS)", "park_no": 1239, "name": "Fountain", "artist": null, "owner": "CPD", "hash": "b3ab7cb66014f517d0c0389618498f62" }, "geometry": { "type": "MultiPoint", "coordinates": [ [ -87.628160012759068, 41.901738320976499 ] ] } },
{ "type": "Feature", "properties": { "park": "MARQUETTE (JACQUES)", "park_no": 10, "name": "Darius & Girenas Memorial", "artist": "Raout Josset", "owner": "CPD", "hash": "11175d46346880ff07ce6c5f05a78407" }, "geometry": { "type": "MultiPoint", "coordinates": [ [ -87.693731093043667, 41.771521669078332 ] ] } },
{ "type": "Feature", "properties": { "park": "McKINLEY (WILLIAM)", "park_no": 23, "name": "William McKinley", "artist": "Charles Mulligan", "owner": "CPD", "hash": "d692675ac11471c451f8760c22d334be" }, "geometry": { "type": "MultiPoint", "coordinates": [ [ -87.683813221281923, 41.826282533680676 ] ] } },
{ "type": "Feature", "properties": { "park": "MID-NORTH", "park_no": 1206, "name": "Fountain", "artist": "Gast Monuments", "owner": null, "hash": "ad475b5a9ac3841a9cdbac26aa343d69" }, "geometry": { "type": "MultiPoint", "coordinates": [ [ -87.639052423557033, 41.923603950171291 ] ] } },
{ "type": "Feature", "properties": { "park": "MIDWAY PLAISANCE", "park_no": 1268, "name": "Cheney-Goode Memorial", "artist": "South Park Commission Architects", "owner": "CPD", "hash": "44b49a2e47202a74f3b32d4a6676a8ea" }, "geometry": { "type": "MultiPoint", "coordinates": [ [ -87.588328935653152, 41.787031810339869 ] ] } },
{ "type": "Feature", "properties": { "park": "MIDWAY PLAISANCE", "park_no": 1268, "name": "Thomas Garrigue Masaryk (The Blanik Knight)", "artist": "Albin Polásek", "owner": "CPD", "hash": "e60e3834aadc57d08d1a27271af65339" }, "geometry": { "type": "MultiPoint", "coordinates": [ [ -87.59014909806892, 41.78693640195246 ] ] } },
{ "type": "Feature", "properties": { "park": "MIDWAY PLAISANCE", "park_no": 1268, "name": "Carl von Linne", "artist": "Frithiof Kjellberg", "owner": "CPD", "hash": "9ab6f79b9e9ac99dfae51ec97b5454ef" }, "geometry": { "type": "MultiPoint", "coordinates": [ [ -87.599605253785867, 41.787529606136367 ] ] } },
{ "type": "Feature", "properties": { "park": "OZ", "park_no": 423, "name": "Tin Man", "artist": "John Kearney", "owner": "CPD", "hash": "7555b06523c3cc28b133ca1c9e280f2b" }, "geometry": { "type": "MultiPoint", "coordinates": [ [ -87.647438058652568, 41.921655334054918 ] ] } },
{ "type": "Feature", "properties": { "park": "MONUMENT", "park_no": 57, "name": "WWI Monument (Honor Roll for Vets)", "artist": "James J. Egan", "owner": "CPD", "hash": "35758963f9d3b079d79886e11d083f53" }, "geometry": { "type": "MultiPoint", "coordinates": [ [ -87.818113679586517, 42.001749246481481 ] ] } },
{ "type": "Feature", "properties": { "park": "MOUNT GREENWOOD", "park_no": 251, "name": "Playground Art", "artist": "CPAG", "owner": "CPD", "hash": "86f6bef8dce2568008d7ac54d112cccb" }, "geometry": { "type": "MultiPoint", "coordinates": [ [ -87.712302405604007, 41.690946500217336 ] ] } },
{ "type": "Feature", "properties": { "park": "NICHOLS (JOHN FOUNTAIN)", "park_no": 277, "name": "Bird of Peace (Guarding the Nest, the Egg)", "artist": "Cosmo Campoli", "owner": "CPD", "hash": "acc4a411226bb7f523fcadb10d02bdbd" }, "geometry": { "type": "MultiPoint", "coordinates": [ [ -87.593379634017339, 41.799187601801414 ] ] } },
{ "type": "Feature", "properties": { "park": "NICHOLS (JOHN FOUNTAIN)", "park_no": 277, "name": "North Fountain", "artist": "Maria Whiteman", "owner": "CPD", "hash": "2f985a96e2c16039c1c0df8ed89991d9" }, "geometry": { "type": "MultiPoint", "coordinates": [ [ -87.593660131188869, 41.799169433054885 ] ] } },
{ "type": "Feature", "properties": { "park": "NICHOLS (JOHN FOUNTAIN)", "park_no": 277, "name": "South Fountain", "artist": "Gary Wojcik", "owner": "CPD", "hash": "ea1ad3301f1a5794e8de8597722aad04" }, "geometry": { "type": "MultiPoint", "coordinates": [ [ -87.59445098840979, 41.795389334910588 ] ] } },
{ "type": "Feature", "properties": { "park": "NORTHERLY ISLAND", "park_no": 34, "name": "America's Courtyard", "artist": "Denise Milan, Ary R. Perez", "owner": "CPD", "hash": "49e5d0f80c6c6c2e34dcd6e6f8c542b2" }, "geometry": { "type": "MultiPoint", "coordinates": [ [ -87.606549665530849, 41.865641648995101 ] ] } },
{ "type": "Feature", "properties": { "park": "NORTHERLY ISLAND", "park_no": 34, "name": "Copernicus Monument", "artist": "Bronislaw Koniuszy", "owner": "COD", "hash": "848e20852841012376b3a55dd7afe91f" }, "geometry": { "type": "MultiPoint", "coordinates": [ [ -87.607789387132129, 41.866348985981688 ] ] } },
{ "type": "Feature", "properties": { "park": "NORTHERLY ISLAND", "park_no": 34, "name": "Karel Havlicek", "artist": "Joseph Strachovsky", "owner": "CPD", "hash": "1cb1acdd1babe20ec239d369c4cc7c2a" }, "geometry": { "type": "MultiPoint", "coordinates": [ [ -87.61044895238301, 41.866319124002331 ] ] } },
{ "type": "Feature", "properties": { "park": "NORTHERLY ISLAND", "park_no": 34, "name": "Thaddeus Kosciusko Monument", "artist": "Kasimir Chodzinski", "owner": "CPD", "hash": "c56948669c077bf7858e1884b33a233f" }, "geometry": { "type": "MultiPoint", "coordinates": [ [ -87.612500355314964, 41.866279555148388 ] ] } },
{ "type": "Feature", "properties": { "park": "NORTHERLY ISLAND", "park_no": 34, "name": "Man Enters the Cosmos", "artist": "Henry Moore", "owner": "CPD", "hash": "56c5fc180b99095e564af018c3aefcd8" }, "geometry": { "type": "MultiPoint", "coordinates": [ [ -87.607106296710057, 41.866758537664531 ] ] } },
{ "type": "Feature", "properties": { "park": "NORTHERLY ISLAND", "park_no": 34, "name": "Spiral Galaxy", "artist": "John David Mooney", "owner": "Adler Planetarium", "hash": "0292e9cb3c80d14f304c3f2a1eaca48b" }, "geometry": { "type": "MultiPoint", "coordinates": [ [ -87.607177254222805, 41.866001197294466 ] ] } },
{ "type": "Feature", "properties": { "park": "OGDEN (WILLIAM) PLAZA", "park_no": 477, "name": "Floor Clock II", "artist": "Vito Acconci", "owner": "CPD", "hash": "4c0110985f198753985a1bb95064b602" }, "geometry": { "type": "MultiPoint", "coordinates": [ [ -87.619892028322113, 41.890264247522822 ] ] } },
{ "type": "Feature", "properties": { "park": "OWENS (JESSE)", "park_no": 237, "name": "Playground Art", "artist": "CPAG", "owner": "CPD", "hash": "ee266109914c88c0c84e2104495b0e5a" }, "geometry": { "type": "MultiPoint", "coordinates": [ [ -87.574392750584821, 41.734855619002658 ] ] } },
{ "type": "Feature", "properties": { "park": "OZ", "park_no": 423, "name": "Cowardly Lion", "artist": "John Kearney", "owner": "CPD", "hash": "b10c12579a27a2531bc8ea92202eb2c6" }, "geometry": { "type": "MultiPoint", "coordinates": [ [ -87.643914249725441, 41.92021434641817 ] ] } },
{ "type": "Feature", "properties": { "park": "OZ", "park_no": 423, "name": "Dorothy and Toto", "artist": "John Kearney", "owner": "CPD", "hash": "d923aa8d08fd505b7f7f38d6dac72765" }, "geometry": { "type": "MultiPoint", "coordinates": [ [ -87.646216950459092, 41.921696692695853 ] ] } },
{ "type": "Feature", "properties": { "park": "OZ", "park_no": 423, "name": "Scarecrow", "artist": "John Kearney", "owner": "CPD", "hash": "be65950b17fb77c93e9f4ae5975af15f" }, "geometry": { "type": "MultiPoint", "coordinates": [ [ -87.643971191845225, 41.92172105927154 ] ] } },
{ "type": "Feature", "properties": { "park": "PARK NO. 474", "park_no": 474, "name": "Man on a Bench", "artist": "George Segal", "owner": "Illinois Institute of Technology", "hash": "9ecffc01573c88cd2e9061a56e66f303" }, "geometry": { "type": "MultiPoint", "coordinates": [ [ -87.627601875549871, 41.835510129957662 ] ] } },
{ "type": "Feature", "properties": { "park": "PARK NO. 532", "park_no": 532, "name": "Restoration", "artist": "Milton Mizenburg Jr.", "owner": null, "hash": "7763b0e5cc0ddb445b85dee6e60bf80f" }, "geometry": { "type": "MultiPoint", "coordinates": [ [ -87.600578450689511, 41.819965055185854 ] ] } },
{ "type": "Feature", "properties": { "park": "RENAISSANCE", "park_no": 509, "name": "Sculptural Fountain", "artist": "Jerzy Kenar", "owner": "CPD", "hash": "6087137fd54239fbfe9073e10d9e180f" }, "geometry": { "type": "MultiPoint", "coordinates": [ [ -87.656103051329296, 41.750719218125532 ] ] } },
{ "type": "Feature", "properties": { "park": "SENN (NICHOLAS)", "park_no": 227, "name": "The Young Lincoln", "artist": "Charles Keck", "owner": "CPD", "hash": "49221ee2fdc131de90f249795bc0e0bb" }, "geometry": { "type": "MultiPoint", "coordinates": [ [ -87.66943993559731, 41.989774647876189 ] ] } },
{ "type": "Feature", "properties": { "park": "SKINNER (MARK)", "park_no": 211, "name": "Playground Dragon", "artist": "CPAG", "owner": "CPD", "hash": "a9588700fcf5e97976e15e46723864ec" }, "geometry": { "type": "MultiPoint", "coordinates": [ [ -87.659872858363613, 41.879381666141811 ] ] } },
{ "type": "Feature", "properties": { "park": "PALMISANO (HENRY)", "park_no": 531, "name": "Entry Fountain", "artist": "Ernest Wong", "owner": "CPD", "hash": "7d2e4666523b361e2d098ccde91e2aad" }, "geometry": { "type": "MultiPoint", "coordinates": [ [ -87.64693135707347, 41.84422553072671 ] ] } },
{ "type": "Feature", "properties": { "park": "SUN YAT-SEN", "park_no": 451, "name": "Dr. Sun Yat-Sen", "artist": null, "owner": "CPD", "hash": "bf2ec1d76167d081938fe20ae14f5041" }, "geometry": { "type": "MultiPoint", "coordinates": [ [ -87.634524399339725, 41.848122597843826 ] ] } },
{ "type": "Feature", "properties": { "park": "TOUHY (PATRICK)", "park_no": 246, "name": "The Receptor", "artist": "Tamsie Ringler", "owner": "Tamsie Ringler", "hash": "22304dfde8c34a883f84312ef4766bba" }, "geometry": { "type": "MultiPoint", "coordinates": [ [ -87.674853025667701, 42.015086211624855 ] ] } },
{ "type": "Feature", "properties": { "park": "UNION", "park_no": 210, "name": "James Connolly Monument", "artist": "Tom White", "owner": "CPD", "hash": "4432190f7e2e2a6d67a541d44acc33c6" }, "geometry": { "type": "MultiPoint", "coordinates": [ [ -87.666535583543563, 41.882633773934472 ] ] } },
{ "type": "Feature", "properties": { "park": "UNION", "park_no": 210, "name": "Carter Harrison Memorial", "artist": "Frederick C. Hibbard", "owner": "CPD", "hash": "68ab79fffac72ea5cb708a91ebdacd12" }, "geometry": { "type": "MultiPoint", "coordinates": [ [ -87.665830115601153, 41.883034641605086 ] ] } },
{ "type": "Feature", "properties": { "park": "WARD (A. MONTGOMERY)", "park_no": 511, "name": "Commemorative Ground Ring", "artist": "Sheila Klein", "owner": "CPD", "hash": "999005ea79d63e0ceb8f493f432df2cf" }, "geometry": { "type": "MultiPoint", "coordinates": [ [ -87.641669535855129, 41.893707394977888 ] ] } },
{ "type": "Feature", "properties": { "park": "WASHINGTON (GEORGE)", "park_no": 21, "name": "Drexel Fountain", "artist": "Henry Manger", "owner": "COC", "hash": "fccb6ab8059513b8ba90824ab8131153" }, "geometry": { "type": "MultiPoint", "coordinates": [ [ -87.604463434749263, 41.801891409278348 ] ] } },
{ "type": "Feature", "properties": { "park": "WASHINGTON (GEORGE)", "park_no": 21, "name": "Fountain of Time", "artist": "Lorado Taft", "owner": "CPD", "hash": "0c7b0dcd5d57b5656e7c7d80f8f359ae" }, "geometry": { "type": "MultiPoint", "coordinates": [ [ -87.607697216328418, 41.786727212617308 ] ] } },
{ "type": "Feature", "properties": { "park": "WASHINGTON (GEORGE)", "park_no": 21, "name": "Gotthold Ephraim Lessing", "artist": "Albin Polasek", "owner": "CPD", "hash": "76f0e1cab09826fcb6a8e0926a75b6e5" }, "geometry": { "type": "MultiPoint", "coordinates": [ [ -87.606510178667207, 41.794458255061947 ] ] } },
{ "type": "Feature", "properties": { "park": "WASHINGTON (GEORGE)", "park_no": 21, "name": "George Washington Monument", "artist": "Daniel Chester French, Edward C. Potter", "owner": "COC", "hash": "9b64994bb8618e1b251b77bdc4f31792" }, "geometry": { "type": "MultiPoint", "coordinates": [ [ -87.616434654267493, 41.802558121296578 ] ] } },
{ "type": "Feature", "properties": { "park": "WASHINGTON (GEORGE)", "park_no": 21, "name": "Playground Art", "artist": "CPAG", "owner": "CPD", "hash": "71eeab1b0301bb0390c896b15178052b" }, "geometry": { "type": "MultiPoint", "coordinates": [ [ -87.614739812512326, 41.791827683519386 ] ] } },
{ "type": "Feature", "properties": { "park": "WASHINGTON (HAROLD)", "park_no": 494, "name": "Ecstasy", "artist": "Virginio Ferrari", "owner": "CPD", "hash": "26792f2dff9e81f137db631878d3a3d5" }, "geometry": { "type": "MultiPoint", "coordinates": [ [ -87.582383985685553, 41.802644467922605 ] ] } },
{ "type": "Feature", "properties": { "park": "WASHINGTON SQUARE", "park_no": 1244, "name": "McCormick Fountain", "artist": null, "owner": "CPD", "hash": "c97240f71d4e1eba77d9c69a85aaffc8" }, "geometry": { "type": "MultiPoint", "coordinates": [ [ -87.630583683405391, 41.899272258523403 ] ] } },
{ "type": "Feature", "properties": { "park": "WICKER (CHARLES, JOEL)", "park_no": 214, "name": "Gurgolye Fountain", "artist": "Robinson Iron Works", "owner": "CPD", "hash": "8d25de6af2f5027bc5b3604338d919b4" }, "geometry": { "type": "MultiPoint", "coordinates": [ [ -87.676728886568952, 41.907688951247792 ] ] } },
{ "type": "Feature", "properties": { "park": "WICKER (CHARLES, JOEL)", "park_no": 214, "name": "Charles Gustave Wicker", "artist": "Nancy Deborah Wicker", "owner": "CPD", "hash": "85c7ecf76d2745532a070e5e2367e158" }, "geometry": { "type": "MultiPoint", "coordinates": [ [ -87.677172030125107, 41.90779953649227 ] ] } },
{ "type": "Feature", "properties": { "park": "BURNHAM (DANIEL)", "park_no": 27, "name": "Balbo Monument", "artist": "Capraro & Komar", "owner": "CPD", "hash": "7c943ee48034284706c4e94eab1412d8" }, "geometry": { "type": "MultiPoint", "coordinates": [ [ -87.613551682144106, 41.861493144098525 ] ] } },
{ "type": "Feature", "properties": { "park": "GRANT (ULYSSES)", "park_no": 24, "name": "Artists and Automobiles", "artist": "Dessa Kirk, Lucy Slivinski, John Mason", "owner": "Dessa Kirk, Lucy Slivinski, John Mason", "hash": "4e521938ab56d26e675da30d3582c1c7" }, "geometry": { "type": "MultiPoint", "coordinates": [ [ -87.621477106111911, 41.875002934803632 ] ] } },
{ "type": "Feature", "properties": { "park": "GRANT (ULYSSES)", "park_no": 24, "name": "Magdalene", "artist": "Dessa Kirk", "owner": "Dessa Kirk", "hash": "d10403dd7f60eff5094b010568a0395f" }, "geometry": { "type": "MultiPoint", "coordinates": [ [ -87.623801182063715, 41.87573410843752 ] ] } },
{ "type": "Feature", "properties": { "park": "KENNEDY (DENNIS)", "park_no": 48, "name": "Korean War Memorial", "artist": "Maurice Moore Memorials", "owner": "CPD", "hash": "671b6089fe0435420721b3ba6f30c392" }, "geometry": { "type": "MultiPoint", "coordinates": [ [ -87.681369580103677, 41.688002376461817 ] ] } },
{ "type": "Feature", "properties": { "park": "LINCOLN (ABRAHAM)", "park_no": 100, "name": "Fountain Girl", "artist": "George Wade", "owner": "CPD", "hash": "357a23d3223da3c75f9f9915e42f53e4" }, "geometry": { "type": "MultiPoint", "coordinates": [ [ -87.62932334090128, 41.912252846980678 ] ] } },
{ "type": "Feature", "properties": { "park": "LINCOLN (ABRAHAM)", "park_no": 100, "name": "William C. Niesen Memorial Fountain", "artist": null, "owner": "CPD", "hash": "6e121f496eb5b0c5cefdb7868fe937d4" }, "geometry": { "type": "MultiPoint", "coordinates": [ [ -87.630198319665311, 41.915126902067897 ] ] } },
{ "type": "Feature", "properties": { "park": "MERRIMAC", "park_no": 256, "name": "Veteran's Memorial", "artist": "Gast Monuments Inc.", "owner": null, "hash": "2959a4b5ecde716928cca52ff1a5e009" }, "geometry": { "type": "MultiPoint", "coordinates": [ [ -87.786272319482208, 41.952605659888285 ] ] } },
{ "type": "Feature", "properties": { "park": "NORTHERLY ISLAND", "park_no": 34, "name": "Daphne", "artist": "Dessa Kirk", "owner": "CPD", "hash": "09ad33937f519213be2755f5a3ff5af7" }, "geometry": { "type": "MultiPoint", "coordinates": [ [ -87.608220639457798, 41.861222820786509 ] ] } },
{ "type": "Feature", "properties": { "park": "OGDEN (WILLIAM)", "park_no": 8, "name": "World War II Memorial Fountain", "artist": "Frederick C. Hibbard", "owner": "CPD", "hash": "d51fabfc93994680216d1634921b6b28" }, "geometry": { "type": "MultiPoint", "coordinates": [ [ -87.655824742651646, 41.775040709868364 ] ] } },
{ "type": "Feature", "properties": { "park": "TOM (PING) MEML.", "park_no": 481, "name": "Ping Tom Bust", "artist": "Liao Huilan", "owner": "CPD", "hash": "4c4ae13ee565b6dcb864db770413a99e" }, "geometry": { "type": "MultiPoint", "coordinates": [ [ -87.634906591572445, 41.856945244470928 ] ] } },
{ "type": "Feature", "properties": { "park": "SENECA", "park_no": 1242, "name": "Ben", "artist": "Deborah Butterfield", "owner": "CPD", "hash": "148f2f77045a5d686d9f8b92ee4d41e8" }, "geometry": { "type": "MultiPoint", "coordinates": [ [ -87.622241239416468, 41.897168629702293 ] ] } },
{ "type": "Feature", "properties": { "park": "TRUMBULL (LYMAN)", "park_no": 16, "name": "WWII Memorial Fountain", "artist": "Frederick C. Hibbard", "owner": "CPD", "hash": "b7ae080b23e17a98b6674b32724312f8" }, "geometry": { "type": "MultiPoint", "coordinates": [ [ -87.564726937361129, 41.706415936814487 ] ] } },
{ "type": "Feature", "properties": { "park": "WARREN (LAURENCE)", "park_no": 428, "name": "Circle of Nature", "artist": "Lynn Takata", "owner": "CPD", "hash": "d7fc52dde418af24ceb4598466a76163" }, "geometry": { "type": "MultiPoint", "coordinates": [ [ -87.688921115509402, 42.001991475401915 ] ] } },
{ "type": "Feature", "properties": { "park": "WASHINGTON (GEORGE)", "park_no": 21, "name": "Spirit of DuSable Series", "artist": "Jill N. Parker, Lawrence E. Taylor, Ausbra Ford", "owner": "CPD", "hash": "c971d5239cca29a0dffde47adc3ab6a2" }, "geometry": { "type": "MultiPoint", "coordinates": [ [ -87.607178750738711, 41.792979193524658 ] ] } },
{ "type": "Feature", "properties": { "park": "WEST PULLMAN", "park_no": 225, "name": "WWI War Memorial", "artist": null, "owner": "CPD", "hash": "94e57e94b27437ae3b4c3b73d820126c" }, "geometry": { "type": "MultiPoint", "coordinates": [ [ -87.630864102591488, 41.670450678638794 ] ] } },
{ "type": "Feature", "properties": { "park": "LINCOLN (ABRAHAM)", "park_no": 100, "name": "East Gate Arch", "artist": "Greg & Camille Leavitt", "owner": "Lincoln Park Zoo", "hash": "1e450baaf6dc9fa2e7198765f796d3d7" }, "geometry": { "type": "MultiPoint", "coordinates": [ [ -87.632309148764605, 41.921948396927959 ] ] } },
{ "type": "Feature", "properties": { "park": "LINCOLN (ABRAHAM)", "park_no": 100, "name": "Bushman's Head", "artist": null, "owner": "Lincoln Park Zoo", "hash": "765c142637d3ca53cd79a989e59af2a2" }, "geometry": { "type": "MultiPoint", "coordinates": [ [ -87.632190037572244, 41.920185583532053 ] ] } },
{ "type": "Feature", "properties": { "park": "LINCOLN (ABRAHAM)", "park_no": 100, "name": "Elephant Drinking Fountain", "artist": "George Suyeoka", "owner": "Lincoln Park Zoo", "hash": "2eb859a7c2accfa4c17f95191a18f49f" }, "geometry": { "type": "MultiPoint", "coordinates": [ [ -87.633402307454105, 41.923028718445984 ] ] } },
{ "type": "Feature", "properties": { "park": "LINCOLN (ABRAHAM)", "park_no": 100, "name": "Eugene Field Memorial", "artist": "Edward McCartan", "owner": "CPD", "hash": "34f4f4ef63e5d4aa04a3dd3d575375f6" }, "geometry": { "type": "MultiPoint", "coordinates": [ [ -87.632163406068955, 41.921143301696638 ] ] } },
{ "type": "Feature", "properties": { "park": "PORTAGE", "park_no": 147, "name": "Canoe Sculpture", "artist": "Phil Schuster, CPAG", "owner": null, "hash": "d60566a52660f54730592e9f7ec90136" }, "geometry": { "type": "MultiPoint", "coordinates": [ [ -87.766565870528453, 41.954455225584297 ] ] } },
{ "type": "Feature", "properties": { "park": "PARK NO. 554", "park_no": 554, "name": "Spider Sculpture", "artist": "Phil Schuster, CPAG", "owner": null, "hash": "93c99f492078c535c0598b8fa0604a1f" }, "geometry": { "type": "MultiPoint", "coordinates": [ [ -87.704637199769891, 41.913968692684499 ] ] } },
{ "type": "Feature", "properties": { "park": "LINCOLN (ABRAHAM)", "park_no": 100, "name": "For the Young at Heart", "artist": "George Suyeoka", "owner": "Lincoln Park Zoo", "hash": "a30cb0283b7ae1ae5219d570f5c8f75f" }, "geometry": { "type": "MultiPoint", "coordinates": [ [ -87.635185711672847, 41.921110443792614 ] ] } },
{ "type": "Feature", "properties": { "park": "LINCOLN (ABRAHAM)", "park_no": 100, "name": "Gorilla", "artist": null, "owner": "Lincoln Park Zoo", "hash": "de331450c57f9a461b67c3cf84987031" }, "geometry": { "type": "MultiPoint", "coordinates": [ [ -87.632294434270264, 41.91988116971887 ] ] } },
{ "type": "Feature", "properties": { "park": "LINCOLN (ABRAHAM)", "park_no": 100, "name": "Heron", "artist": "H. Wheatley Allen", "owner": "Lincoln Park Zoo", "hash": "25ff19e0f9776a001d6c634cbc66adb8" }, "geometry": { "type": "MultiPoint", "coordinates": [ [ -87.635202846343603, 41.921320956055624 ] ] } },
{ "type": "Feature", "properties": { "park": "GRANT (ULYSSES)", "park_no": 24, "name": "Large Interior Form", "artist": "Henry Moore", "owner": "Art Institute of Chicago", "hash": "0b28e88fd8c6ebe7339154b384c86a43" }, "geometry": { "type": "MultiPoint", "coordinates": [ [ -87.623667246589392, 41.880295373997406 ] ] } },
{ "type": "Feature", "properties": { "park": "LINCOLN (ABRAHAM)", "park_no": 100, "name": "The Lesson", "artist": "Darrell Davis", "owner": "Lincoln Park Zoo", "hash": "e033e0f818581323e2cc1b41590252ee" }, "geometry": { "type": "MultiPoint", "coordinates": [ [ -87.634810400716688, 41.921674085988386 ] ] } },
{ "type": "Feature", "properties": { "park": "LINCOLN (ABRAHAM)", "park_no": 100, "name": "Limestone Lion", "artist": "Kathleen McCullough", "owner": "Lincoln Park Zoo", "hash": "fd7dcce1d2e10f9cae58336f4b396742" }, "geometry": { "type": "MultiPoint", "coordinates": [ [ -87.633058501259427, 41.921968142841976 ] ] } },
{ "type": "Feature", "properties": { "park": "LINCOLN (ABRAHAM)", "park_no": 100, "name": "Lion Fountain", "artist": "George Suyeoka", "owner": "Lincoln Park Zoo", "hash": "a8f3fbe8a8ec7fa81a9693a3af1763e3" }, "geometry": { "type": "MultiPoint", "coordinates": [ [ -87.633920253265075, 41.92134217197237 ] ] } },
{ "type": "Feature", "properties": { "park": "LINCOLN (ABRAHAM)", "park_no": 100, "name": "Lowland Gorilla Family", "artist": "Bill Wieger", "owner": "Lincoln Park Zoo", "hash": "95f255de82e4192d00353dcfd5086684" }, "geometry": { "type": "MultiPoint", "coordinates": [ [ -87.631829911019608, 41.919718713320947 ] ] } },
{ "type": "Feature", "properties": { "park": "LINCOLN (ABRAHAM)", "park_no": 100, "name": "Mother and Baby Pygmy Hippo", "artist": "Henry Mitchell", "owner": "Lincoln Park Zoo", "hash": "74e2d01d406ea90ec4f5a393dceebb01" }, "geometry": { "type": "MultiPoint", "coordinates": [ [ -87.632972217944129, 41.922751203276285 ] ] } },
{ "type": "Feature", "properties": { "park": "LINCOLN (ABRAHAM)", "park_no": 100, "name": "Old Fishing Hole", "artist": "Peter Darro", "owner": "Lincoln Park Zoo", "hash": "effe7208c874914f51339e0117129182" }, "geometry": { "type": "MultiPoint", "coordinates": [ [ -87.633675927289289, 41.920586117936224 ] ] } },
{ "type": "Feature", "properties": { "park": "LINCOLN (ABRAHAM)", "park_no": 100, "name": "Pathfinders", "artist": "Veryl Goodnight", "owner": "Lincoln Park Zoo", "hash": "da95cd37c57fbe8998b17c60c2bd1e49" }, "geometry": { "type": "MultiPoint", "coordinates": [ [ -87.63487098133011, 41.921464046448847 ] ] } },
{ "type": "Feature", "properties": { "park": "LINCOLN (ABRAHAM)", "park_no": 100, "name": "Polar Bear", "artist": "Viktor Bougaev", "owner": "Lincoln Park Zoo", "hash": "65e4d376240cd46d48ab2f1e65fd81e0" }, "geometry": { "type": "MultiPoint", "coordinates": [ [ -87.633793631603467, 41.92404042233607 ] ] } },
{ "type": "Feature", "properties": { "park": "LINCOLN (ABRAHAM)", "park_no": 100, "name": "Rabbit and Butterfly", "artist": "H. Wheatley Allen", "owner": "Lincoln Park Zoo", "hash": "a169fb40d40bcef10458579f8ff2595e" }, "geometry": { "type": "MultiPoint", "coordinates": [ [ -87.634916958262124, 41.920811337191438 ] ] } },
{ "type": "Feature", "properties": { "park": "LINCOLN (ABRAHAM)", "park_no": 100, "name": "Rites of Spring", "artist": "Milton Horn", "owner": "Lincoln Park Zoo", "hash": "decca48ae983af188d4a392a63050b1e" }, "geometry": { "type": "MultiPoint", "coordinates": [ [ -87.6329998711728, 41.919334061171682 ] ] } },
{ "type": "Feature", "properties": { "park": "LINCOLN (ABRAHAM)", "park_no": 100, "name": "Seal and Sea Lion", "artist": "Dino C. Crisanti", "owner": "Lincoln Park Zoo", "hash": "e66dd0b8f307381aff82649b7fb813e4" }, "geometry": { "type": "MultiPoint", "coordinates": [ [ -87.634550094917174, 41.921491115420025 ] ] } },
{ "type": "Feature", "properties": { "park": "LINCOLN (ABRAHAM)", "park_no": 100, "name": "Siblings", "artist": "Rosetta", "owner": "Lincoln Park Zoo", "hash": "cf351f323a0e09ac0d35a0689c9361b2" }, "geometry": { "type": "MultiPoint", "coordinates": [ [ -87.635931974254973, 41.918597342408326 ] ] } },
{ "type": "Feature", "properties": { "park": "LINCOLN (ABRAHAM)", "park_no": 100, "name": "Sunform", "artist": "David L. Rodgers", "owner": "Lincoln Park Zoo", "hash": "6be96e06ff392f8e4e2e9d3f0c367552" }, "geometry": { "type": "MultiPoint", "coordinates": [ [ -87.633190064029193, 41.920597667945827 ] ] } },
{ "type": "Feature", "properties": { "park": "RAINBOW BEACH", "park_no": 1001, "name": "50th Anniversary of the Rainbow Division WWI", "artist": null, "owner": "CPD", "hash": "5d0e0e082b98458157f47ef6d87649c9" }, "geometry": { "type": "MultiPoint", "coordinates": [ [ -87.556310147094933, 41.760435426331561 ] ] } }
]
}
